lazy_srcset/__init__.py
lazy_srcset/apps.py
lazy_srcset/conf.py
lazy_srcset/imagegenerators.py
lazy_srcset/management/__init__.py
lazy_srcset/management/commands/__init__.py
lazy_srcset/management/commands/imagekit_cleanup.py
lazy_srcset/templatetags/__init__.py
lazy_srcset/templatetags/lazy_srcset.py
django_lazy_srcset-1.0.5.dist-info/LICENSE
django_lazy_srcset-1.0.5.dist-info/METADATA
django_lazy_srcset-1.0.5.dist-info/WHEEL
django_lazy_srcset-1.0.5.dist-info/dependency_links.txt
django_lazy_srcset-1.0.5.dist-info/top_level.txt
django_lazy_srcset-1.0.5.dist-info/RECORD
