Metadata-Version: 2.1
Name: django-lazy-srcset
Version: 1.0.5
Summary: Lazy srcset and responsive image generation for Django. Minimum effort required. No database required.
Home-page: https://github.com/Quantra/django-lazy-srcset
Author: Vince Coleman
Author-email: vince@shystudios.co.uk
License: MIT
Project-URL: Source, https://github.com/Quantra/django-lazy-srcset
Keywords: django,django-lazy-srcset,django lazy srcset,django srcset,django responsive images,django responsive
Classifier: Environment :: Web Environment
Classifier: Framework :: Django
Classifier: Framework :: Django :: 3.2
Classifier: Framework :: Django :: 4.0
Classifier: Framework :: Django :: 4.1
Classifier: Framework :: Django :: 4.2
Classifier: Intended Audience :: Developers
Classifier: Development Status :: 4 - Beta
Classifier: License :: OSI Approved :: MIT License
Classifier: Operating System :: OS Independent
Classifier: Programming Language :: Python
Classifier: Programming Language :: Python :: 3
Classifier: Programming Language :: Python :: 3 :: Only
Classifier: Programming Language :: Python :: 3.7
Classifier: Programming Language :: Python :: 3.8
Classifier: Programming Language :: Python :: 3.9
Classifier: Programming Language :: Python :: 3.10
Classifier: Programming Language :: Python :: 3.11
Classifier: Programming Language :: Python :: 3.12
Classifier: Topic :: Internet :: WWW/HTTP
Classifier: Topic :: Internet :: WWW/HTTP :: Dynamic Content
Classifier: Topic :: Internet :: WWW/HTTP :: Site Management
Requires-Python: >=3.7
License-File: LICENSE
Requires-Dist: Django>=3.2
Requires-Dist: Pillow
Requires-Dist: django-imagekit
